<?xml version="1.0" encoding="utf-8"?>
<!-- Copyright (c) CLMS UK. All rights reserved.-->
<!-- Licensed under the Custom License. See LICENSE file in the project root for full license information.-->
<!-- This was autogenerated by zAppDev. -->
<Locales Lang="en-us">
    <Loc Key="RES_TOOLTIP_Canvas" Value="" />
    <Loc Key="RES_TOOLTIP_Panel" Value="" />
    <Loc Key="RES_TOOLTIP_PanelHeader" Value="" />
    <Loc Key="RES_TOOLTIP_PanelContainer" Value="" />
    <Loc Key="RES_GRID_Table_NoData" Value="No records." />
    <Loc Key="RES_GRID_Table_ADD_ROW" Value="Add row" />
    <Loc Key="RES_GRID_Table_WARNING_MESSAGE" Value="" />
    <Loc Key="RES_GRID_Table_MULTI_WARNING_MESSAGE" Value="" />
    <Loc Key="RES_Table_ConfirmationMessage" Value="Are you sure you want to execute this action?" />
    <Loc Key="RES_TOOLTIP_Table" Value="" />
    <Loc Key="RES_TOOLTIP_Row" Value="" />
    <Loc Key="RES_TOOLTIP_Cell11" Value="" />
    <Loc Key="RES_TOOLTIP_Row1" Value="" />
    <Loc Key="RES_TOOLTIP_Cell10" Value="" />
    <Loc Key="RES_Layout1_ConfirmationMessage" Value="Are you sure you want to execute this action?" />
    <Loc Key="RES_TOOLTIP_Layout1" Value="" />
    <Loc Key="RES_TOOLTIP_Row4" Value="" />
    <Loc Key="RES_TOOLTIP_Cell7" Value="" />
    <Loc Key="RES_TOOLTIP_Cell71" Value="" />
    <Loc Key="RES_Layout_ConfirmationMessage" Value="Are you sure you want to execute this action?" />
    <Loc Key="RES_TOOLTIP_Layout" Value="" />
    <Loc Key="RES_TOOLTIP_Row2" Value="" />
    <Loc Key="RES_TOOLTIP_Cell3" Value="" />
    <Loc Key="RES_LABEL_lblName" Value="Name:" />
    <Loc Key="RES_TOOLTIP_lblName" Value="" />
    <Loc Key="RES_TOOLTIP_Cell1" Value="" />
    <Loc Key="RES_LABEL_lblNameds" Value="Label" />
    <Loc Key="RES_TOOLTIP_lblNameds" Value="" />
    <Loc Key="RES_TOOLTIP_Row21" Value="" />
    <Loc Key="RES_TOOLTIP_Cell31" Value="" />
    <Loc Key="RES_LABEL_lblEmail" Value="Email:" />
    <Loc Key="RES_TOOLTIP_lblEmail" Value="" />
    <Loc Key="RES_TOOLTIP_Cell4" Value="" />
    <Loc Key="RES_LABEL_lblEmailds" Value="Label" />
    <Loc Key="RES_TOOLTIP_lblEmailds" Value="" />
    <Loc Key="RES_TOOLTIP_Row211" Value="" />
    <Loc Key="RES_TOOLTIP_Cell311" Value="" />
    <Loc Key="RES_LABEL_lblCompanyDescription" Value="Country:" />
    <Loc Key="RES_TOOLTIP_lblCompanyDescription" Value="" />
    <Loc Key="RES_TOOLTIP_Cell6" Value="CompanyDescription" />
    <Loc Key="RES_LABEL_txtName1" Value="Label" />
    <Loc Key="RES_TOOLTIP_txtName1" Value="" />
    <Loc Key="RES_TOOLTIP_Cell8" Value="" />
    <Loc Key="RES_LABEL_Label" Value="Edit" />
    <Loc Key="RES_TOOLTIP_Label" Value="" />
    <Loc Key="RES_TOOLTIP_Row3" Value="" />
    <Loc Key="RES_TOOLTIP_Cell2" Value="" />
    <Loc Key="RES_LABEL_lblCompanyDataSetRecords" Value="Records:" />
    <Loc Key="RES_TOOLTIP_lblCompanyDataSetRecords" Value="" />
    <Loc Key="RES_LABEL_lblCompanyDataSetTotalItems" Value="Label" />
    <Loc Key="RES_TOOLTIP_lblCompanyDataSetTotalItems" Value="" />
    <Loc Key="RES_TOOLTIP_PanelFooter" Value="" />
    <Loc Key="RES_PAGETITLE_Index" Value="Results" />
    <Loc Key="RES_Canvas_ConfirmationMessage" Value="Are you sure you want to execute this action?" />
    <Loc Key="RES_Panel_ConfirmationMessage" Value="Are you sure you want to execute this action?" />
    <Loc Key="RES_PanelHeader_ConfirmationMessage" Value="Are you sure you want to execute this action?" />
    <Loc Key="RES_PanelContainer_ConfirmationMessage" Value="Are you sure you want to execute this action?" />
    <Loc Key="RES_Row1_ConfirmationMessage" Value="Are you sure you want to execute this action?" />
    <Loc Key="RES_Cell10_ConfirmationMessage" Value="Are you sure you want to execute this action?" />
    <Loc Key="RES_Row4_ConfirmationMessage" Value="Are you sure you want to execute this action?" />
    <Loc Key="RES_Cell7_ConfirmationMessage" Value="Are you sure you want to execute this action?" />
    <Loc Key="RES_Cell71_ConfirmationMessage" Value="Are you sure you want to execute this action?" />
    <Loc Key="RES_Row2_ConfirmationMessage" Value="Are you sure you want to execute this action?" />
    <Loc Key="RES_Cell3_ConfirmationMessage" Value="Are you sure you want to execute this action?" />
    <Loc Key="RES_lblName_ConfirmationMessage" Value="Are you sure you want to execute this action?" />
    <Loc Key="RES_Cell1_ConfirmationMessage" Value="Are you sure you want to execute this action?" />
    <Loc Key="RES_lblNameds_ConfirmationMessage" Value="Are you sure you want to execute this action?" />
    <Loc Key="RES_Row21_ConfirmationMessage" Value="Are you sure you want to execute this action?" />
    <Loc Key="RES_Cell31_ConfirmationMessage" Value="Are you sure you want to execute this action?" />
    <Loc Key="RES_lblEmail_ConfirmationMessage" Value="Are you sure you want to execute this action?" />
    <Loc Key="RES_Cell4_ConfirmationMessage" Value="Are you sure you want to execute this action?" />
    <Loc Key="RES_lblEmailds_ConfirmationMessage" Value="Are you sure you want to execute this action?" />
    <Loc Key="RES_Row211_ConfirmationMessage" Value="Are you sure you want to execute this action?" />
    <Loc Key="RES_Cell311_ConfirmationMessage" Value="Are you sure you want to execute this action?" />
    <Loc Key="RES_lblCompanyDescription_ConfirmationMessage" Value="Are you sure you want to execute this action?" />
    <Loc Key="RES_Cell6_ConfirmationMessage" Value="Are you sure you want to execute this action?" />
    <Loc Key="RES_txtName1_ConfirmationMessage" Value="Are you sure you want to execute this action?" />
    <Loc Key="RES_Cell8_ConfirmationMessage" Value="Are you sure you want to execute this action?" />
    <Loc Key="RES_Button_ConfirmationMessage" Value="Are you sure you want to execute this action?" />
    <Loc Key="RES_Label_ConfirmationMessage" Value="Are you sure you want to execute this action?" />
    <Loc Key="RES_Row_ConfirmationMessage" Value="Are you sure you want to execute this action?" />
    <Loc Key="RES_Cell11_ConfirmationMessage" Value="Are you sure you want to execute this action?" />
    <Loc Key="RES_Row3_ConfirmationMessage" Value="Are you sure you want to execute this action?" />
    <Loc Key="RES_Cell2_ConfirmationMessage" Value="Are you sure you want to execute this action?" />
    <Loc Key="RES_lblCompanyDataSetRecords_ConfirmationMessage" Value="Are you sure you want to execute this action?" />
    <Loc Key="RES_lblCompanyDataSetTotalItems_ConfirmationMessage" Value="Are you sure you want to execute this action?" />
    <Loc Key="RES_PanelFooter_ConfirmationMessage" Value="Are you sure you want to execute this action?" />
</Locales>